cleanurl.py
cleanurl-0.1.15.dist-info/LICENSE
cleanurl-0.1.15.dist-info/METADATA
cleanurl-0.1.15.dist-info/WHEEL
cleanurl-0.1.15.dist-info/RECORD
