Metadata-Version: 2.1
Name: cleanurl
Version: 0.1.15
Summary: Remove clutter from URLs and return a canonicalized version
Home-page: https://github.com/xojoc/cleanurl
License: AGPL-3.0-or-later
Keywords: url,canonical
Author: Alexandru Cojocaru
Author-email: hi@xojoc.pw
Requires-Python: >=3.9,<4.0
Classifier: Environment :: Web Environment
Classifier: Intended Audience :: Developers
Classifier: License :: OSI Approved :: GNU Affero General Public License v3 or later (AGPLv3+)
Classifier: Operating System :: OS Independent
Classifier: Programming Language :: Python :: 3
Classifier: Programming Language :: Python :: 3.9
Classifier: Programming Language :: Python :: 3.10
Classifier: Programming Language :: Python :: 3.11
Classifier: Typing :: Typed
Requires-Dist: langcodes (>=3.3.0,<4.0.0)
Project-URL: Repository, https://github.com/xojoc/cleanurl
